{"uuid":"23ea2a40-9f4f-4d07-9134-a579becfd349","description":"\"Wallet in the box Evening\"","tags":["[\"daily\",\"evening\",\"goal\"]"],"mask":"\"++++XXX++++++++++++XX+++X+XX+X++X++++++++++X+XXXX+XX+XXX+XXXXXXX+++++++XX++XX+++X+XXXXXX+++XXXXXXX+X+XXXXXXXX++++XXXXXXXXXXWWWWW\"","modified":"2023-12-25 15:28:50.0","project":["Subsistence","Discipline"],"rtype":"null","recur":"\"1d\"","status":"\"recurring\"","entry":"2023-08-22 19:35:31.0","wait":"2023-08-22 03:00:00.0","scheduled":null,"start":null,"due":"2023-08-22 05:00:00.0","until":null,"end":null}